Metadata-Version: 2.1
Name: linkedin-search-groups-scraper
Version: 1.0.0
Summary: A python library to search keyword in linkedin groups and scrape search results data from linkedin automatically.
Home-page: https://linkedin-api.datakund.com/en/latest/
Author: DataKund
Author-email: datakund@gmail.com
License: Apache License 2.0
Keywords: linkedin python bot_studio scraper group search search-results data web-scraping keyword
Platform: UNKNOWN
